caema_utils/__init__.py
caema_utils/pose_estimation/__init__.py
caema_utils/pose_estimation/estimator.py
caema_utils/pose_estimation/server.py
caema_utils/pose_estimation/models/__init__.py
caema_utils/pose_estimation/models/analyzer.py
caema_utils-0.2.0.dist-info/licenses/LICENSE
caema_utils-0.2.0.dist-info/METADATA
caema_utils-0.2.0.dist-info/WHEEL
caema_utils-0.2.0.dist-info/entry_points.txt
caema_utils-0.2.0.dist-info/top_level.txt
caema_utils-0.2.0.dist-info/RECORD
