Metadata-Version: 2.4
Name: caema-utils
Version: 0.2.0
Summary: A collection of reusable Python modules for AI services
Author-email: CAEMA Solutions <info@caema.com>
Maintainer-email: CAEMA Solutions <info@caema.com>
License: MIT
Project-URL: Homepage, https://github.com/msorozabal/Utils
Project-URL: Documentation, https://github.com/msorozabal/Utils#readme
Project-URL: Repository, https://github.com/msorozabal/Utils.git
Project-URL: Issues, https://github.com/msorozabal/Utils/issues
Keywords: pose-estimation,computer-vision,yolo,biomechanics,ai,utils
Classifier: Development Status :: 4 - Beta
Classifier: Intended Audience :: Developers
Classifier: License :: OSI Approved :: MIT License
Classifier: Operating System :: OS Independent
Classifier: Programming Language :: Python :: 3
Classifier: Programming Language :: Python :: 3.9
Classifier: Programming Language :: Python :: 3.10
Classifier: Programming Language :: Python :: 3.11
Classifier: Programming Language :: Python :: 3.12
Classifier: Topic :: Scientific/Engineering :: Artificial Intelligence
Classifier: Topic :: Scientific/Engineering :: Image Processing
Requires-Python: >=3.9
License-File: LICENSE
Provides-Extra: pose
Requires-Dist: numpy<2.0.0; extra == "pose"
Requires-Dist: ultralytics>=8.1.0; extra == "pose"
Requires-Dist: opencv-python-headless>=4.9.0; extra == "pose"
Provides-Extra: server
Requires-Dist: fastapi>=0.100.0; extra == "server"
Requires-Dist: uvicorn>=0.23.0; extra == "server"
Requires-Dist: python-multipart>=0.0.6; extra == "server"
Provides-Extra: all
Requires-Dist: caema-utils[pose,server]; extra == "all"
Provides-Extra: dev
Requires-Dist: pytest>=7.0.0; extra == "dev"
Requires-Dist: pytest-cov>=4.0.0; extra == "dev"
Requires-Dist: black>=23.0.0; extra == "dev"
Requires-Dist: ruff>=0.1.0; extra == "dev"
Requires-Dist: mypy>=1.0.0; extra == "dev"
Dynamic: license-file
